{"date":"2017-09-27","zones":{"FR":{"avg":46.13,"min":31.01,"max":57.91,"negH":0.0,"hourly":[37.88,34.6,32.94,32.13,32.14,33.7,45.07,54.4,57.91,55.0,51.8,50.6,48.99,47.85,46.95,43.96,44.01,49.09,49.99,54.86,51.46,47.45,44.11,37.94,38.9,34.69,32.79,31.01,31.05,33.4,40.2,50.84,56.19,57.8,56.03,55.59,54.4,53.14,53.35,51.5,50.69,53.13,52.5,55.4,56.41,49.9,43.4,37.26,null,null,null,null,null,null,null,null,null,null,null,null,null,null,null,null,null,null,null,null,null,null,null,null,null,null,null,null,null,null,null,null,null,null,null,null,null,null,null,null,null,null,null,null,null,null,null,null],"peakAvg":52.29,"offAvg":43.05,"genmix":{"nuclear":41641,"solar":1978,"wind":1144,"hydro":6105,"fossil":6543,"biomass":299,"other":0,"total":57710},"renPct":16.0,"domFuel":"Nuclear"}}}