{"date":"2018-09-04","zones":{"FR":{"avg":68.03,"min":51.24,"max":79.62,"negH":0.0,"hourly":[57.13,54.09,52.18,51.24,51.69,54.6,67.09,73.02,74.68,74.91,73.92,73.46,71.06,69.02,68.81,68.55,70.01,72.94,73.99,75.0,null,73.06,69.3,61.82,55.72,54.47,53.56,52.66,53.18,55.32,71.54,75.65,76.76,77.06,76.68,77.05,75.17,72.05,72.69,72.1,74.02,75.57,76.76,79.62,79.33,76.03,70.01,62.74,null,null,null,null,null,null,null,null,null,null,null,null,null,null,null,null,null,null,null,null,null,null,null,null,null,null,null,null,null,null,null,null,null,null,null,null,null,null,null,null,null,null,null,null,null,null,null,null],"peakAvg":74.6,"offAvg":64.63,"genmix":{"nuclear":40612,"solar":2438,"wind":1307,"hydro":6458,"fossil":4768,"biomass":312,"other":0,"total":55895},"renPct":18.3,"domFuel":"Nuclear"}}}