{"date":"2018-06-03","zones":{"FR":{"avg":34.15,"min":8.77,"max":61.79,"negH":0.0,"hourly":[35.97,29.48,26.77,19.37,13.15,8.77,9.61,13.39,14.96,17.28,15.76,19.48,21.22,20.65,20.14,18.81,14.6,18.7,27.6,36.37,32.63,32.04,39.09,35.61,35.57,23.69,18.49,11.21,15.24,20.42,31.86,54.23,61.59,60.12,59.8,60.27,58.16,55.35,52.25,48.95,48.12,56.07,58.27,61.79,57.95,52.93,50.93,44.49,null,null,null,null,null,null,null,null,null,null,null,null,null,null,null,null,null,null,null,null,null,null,null,null,null,null,null,null,null,null,null,null,null,null,null,null,null,null,null,null,null,null,null,null,null,null,null,null],"peakAvg":55.44,"offAvg":23.51,"genmix":{"nuclear":37211,"solar":1620,"wind":1470,"hydro":12125,"fossil":638,"biomass":321,"other":0,"total":53385},"renPct":28.5,"domFuel":"Nuclear"}}}