{"date":"2018-07-20","zones":{"FR":{"avg":51.96,"min":44.05,"max":58.95,"negH":0.0,"hourly":[48.82,45.6,44.49,44.05,44.93,45.04,52.47,57.61,57.93,57.98,57.06,56.69,55.1,54.07,54.03,55.06,56.07,57.91,58.5,58.95,57.98,56.1,56.02,52.57,50.33,45.58,44.73,45.52,44.67,44.4,44.06,46.69,52.52,55.04,55.09,55.18,54.72,50.46,45.0,45.1,47.09,53.12,55.02,55.22,54.96,54.68,57.48,52.2,null,null,null,null,null,null,null,null,null,null,null,null,null,null,null,null,null,null,null,null,null,null,null,null,null,null,null,null,null,null,null,null,null,null,null,null,null,null,null,null,null,null,null,null,null,null,null,null],"peakAvg":52.68,"offAvg":51.59,"genmix":{"nuclear":42919,"solar":1688,"wind":1242,"hydro":8336,"fossil":4224,"biomass":426,"other":0,"total":58835},"renPct":19.1,"domFuel":"Nuclear"}}}