{"date":"2018-12-15","zones":{"FR":{"avg":59.3,"min":46.0,"max":71.1,"negH":0.0,"hourly":[70.33,63.43,58.34,52.74,51.25,50.81,51.76,57.15,67.73,68.4,70.49,68.93,67.58,63.1,58.0,58.72,60.04,62.72,69.83,67.61,60.78,51.56,60.48,59.41,55.19,51.2,49.58,46.74,46.0,46.77,49.11,50.81,51.6,56.72,57.98,58.82,64.44,59.29,57.05,55.87,58.45,67.01,71.1,69.31,68.07,60.6,66.01,57.26,null,null,null,null,null,null,null,null,null,null,null,null,null,null,null,null,null,null,null,null,null,null,null,null,null,null,null,null,null,null,null,null,null,null,null,null,null,null,null,null,null,null,null,null,null,null,null,null],"peakAvg":61.22,"offAvg":58.33,"genmix":{"nuclear":52756,"solar":783,"wind":4483,"hydro":8531,"fossil":7607,"biomass":325,"other":0,"total":74485},"renPct":18.5,"domFuel":"Nuclear"}}}