{"date":"2019-09-09","zones":{"FR":{"avg":39.21,"min":27.56,"max":57.09,"negH":0.0,"hourly":[38.33,34.09,32.81,30.41,29.72,31.88,42.45,47.0,48.58,50.07,48.07,46.77,46.0,45.23,42.64,42.23,41.6,45.14,49.99,57.09,56.95,45.94,40.38,34.35,33.01,32.45,31.0,29.0,27.56,28.0,33.0,44.95,45.93,41.0,36.0,32.6,32.98,32.88,31.3,32.01,34.1,39.18,41.09,42.63,43.29,42.75,35.89,31.7,null,null,null,null,null,null,null,null,null,null,null,null,null,null,null,null,null,null,null,null,null,null,null,null,null,null,null,null,null,null,null,null,null,null,null,null,null,null,null,null,null,null,null,null,null,null,null,null],"peakAvg":37.21,"offAvg":40.21,"genmix":{"nuclear":41155,"solar":2187,"wind":1113,"hydro":6953,"fossil":5115,"biomass":467,"other":0,"total":56990},"renPct":18.0,"domFuel":"Nuclear"}}}