{"date":"2019-01-23","zones":{"FR":{"avg":81.01,"min":51.02,"max":121.46,"negH":0.0,"hourly":[57.99,56.09,55.05,51.19,51.02,55.2,65.28,82.9,92.15,93.65,91.93,90.31,84.96,83.99,85.59,86.87,84.96,90.01,93.9,90.54,78.56,69.6,68.77,65.18,63.16,59.98,58.2,56.52,56.95,61.53,74.9,99.07,113.07,111.23,108.25,103.69,98.33,92.63,89.86,90.45,95.01,106.82,121.46,102.06,89.34,74.43,70.12,65.57,null,null,null,null,null,null,null,null,null,null,null,null,null,null,null,null,null,null,null,null,null,null,null,null,null,null,null,null,null,null,null,null,null,null,null,null,null,null,null,null,null,null,null,null,null,null,null,null],"peakAvg":95.77,"offAvg":73.62,"genmix":{"nuclear":54198,"solar":824,"wind":3473,"hydro":12156,"fossil":10004,"biomass":353,"other":0,"total":81008},"renPct":20.3,"domFuel":"Nuclear"}}}