{"date":"2019-07-04","zones":{"FR":{"avg":32.56,"min":15.76,"max":43.58,"negH":0.0,"hourly":[29.93,28.83,24.89,20.71,15.76,19.99,27.47,35.51,39.72,34.77,31.88,30.89,29.77,29.65,29.53,29.66,29.8,32.98,36.92,43.58,38.23,36.27,39.06,34.9,29.8,29.0,27.8,27.64,27.9,29.08,34.62,39.27,43.27,43.4,38.0,36.6,33.02,31.05,29.68,29.23,30.4,32.97,35.35,38.35,35.91,32.96,39.37,37.34,null,null,null,null,null,null,null,null,null,null,null,null,null,null,null,null,null,null,null,null,null,null,null,null,null,null,null,null,null,null,null,null,null,null,null,null,null,null,null,null,null,null,null,null,null,null,null,null],"peakAvg":35.43,"offAvg":31.12,"genmix":{"nuclear":41132,"solar":2949,"wind":2519,"hydro":8470,"fossil":3125,"biomass":303,"other":0,"total":58498},"renPct":23.8,"domFuel":"Nuclear"}}}