{"date":"2024-02-05","zones":{"FR":{"avg":53.49,"min":1.25,"max":90.36,"negH":0.0,"hourly":[11.28,15.85,8.91,2.71,1.25,7.53,48.09,83.15,90.36,87.36,76.68,69.74,60.0,42.86,51.0,59.71,64.49,76.44,89.13,86.67,80.04,65.69,57.11,48.19,36.8,30.13,20.41,11.83,7.1,23.4,54.26,71.91,80.87,78.68,74.72,60.64,51.08,48.62,49.79,56.44,61.33,71.0,78.77,80.36,65.16,60.17,57.09,52.76,null,null,null,null,null,null,null,null,null,null,null,null,null,null,null,null,null,null,null,null,null,null,null,null,null,null,null,null,null,null,null,null,null,null,null,null,null,null,null,null,null,null,null,null,null,null,null,null],"peakAvg":64.22,"offAvg":48.13}}}