{
  "updated": "2026-06-06T13:11:24.142010Z",
  "countries": {
    "FR": {
      "nuclear": 18887,
      "solar": 3011,
      "wind": 3906,
      "hydro": 3611,
      "fossil": 107,
      "biomass": 383,
      "other": 65,
      "total": 29970
    },
    "DE_LU": {
      "nuclear": 0,
      "solar": 7457,
      "wind": 260,
      "hydro": 2524,
      "fossil": 4906,
      "biomass": 2391,
      "other": 32,
      "total": 17570
    },
    "ES": {
      "nuclear": 1509,
      "solar": 5733,
      "wind": 1417,
      "hydro": 2638,
      "fossil": 2244,
      "biomass": 349,
      "other": 34,
      "total": 13924
    },
    "BE": {
      "nuclear": 0,
      "solar": 842,
      "wind": 866,
      "hydro": 135,
      "fossil": 497,
      "biomass": 119,
      "other": 126,
      "total": 2585
    },
    "NL": {
      "nuclear": 257,
      "solar": 49,
      "wind": 614,
      "hydro": 0,
      "fossil": 1886,
      "biomass": 2,
      "other": 131,
      "total": 2939
    },
    "GB": {
      "nuclear": 0,
      "solar": 0,
      "wind": 0,
      "hydro": 0,
      "fossil": 0,
      "biomass": 0,
      "other": 0,
      "total": 0
    },
    "PT": {
      "nuclear": 0,
      "solar": 478,
      "wind": 351,
      "hydro": 1147,
      "fossil": 322,
      "biomass": 126,
      "other": 13,
      "total": 2437
    }
  }
}