{
  "updated": "2026-07-21T07:27:47.778126Z",
  "countries": {
    "FR": {
      "actual": [
        39950,
        39099,
        38428,
        37794,
        37408,
        37090,
        36928,
        36735,
        36781,
        36650,
        36637,
        36744,
        37434,
        37914,
        38275,
        38695,
        39472,
        40046,
        40568,
        41118,
        41605,
        42404,
        43160,
        43868,
        44483,
        45031,
        45325,
        45633,
        null,
        null,
        null,
        null,
        null,
        null,
        null,
        null,
        null,
        null,
        null,
        null,
        null,
        null,
        null,
        null,
        null,
        null,
        null,
        null,
        null,
        null,
        null,
        null,
        null,
        null,
        null,
        null,
        null,
        null,
        null,
        null,
        null,
        null,
        null,
        null,
        null,
        null,
        null,
        null,
        null,
        null,
        null,
        null,
        null,
        null,
        null,
        null,
        null,
        null,
        null,
        null,
        null,
        null,
        null,
        null,
        null,
        null,
        null,
        null,
        null,
        null,
        null,
        null,
        null,
        null,
        null,
        null
      ],
      "peak": 45633,
      "current": 45633
    },
    "DE_LU": {
      "actual": [
        43509,
        43277,
        43357,
        43237,
        43239,
        43461,
        43440,
        43550,
        43995,
        44244,
        44654,
        45196,
        46441,
        46684,
        47159,
        48427,
        50776,
        52751,
        53838,
        54810,
        55871,
        57870,
        58456,
        59105,
        58616,
        59288,
        59418,
        null,
        null,
        null,
        null,
        null,
        null,
        null,
        null,
        null,
        null,
        null,
        null,
        null,
        null,
        null,
        null,
        null,
        null,
        null,
        null,
        null,
        null,
        null,
        null,
        null,
        null,
        null,
        null,
        null,
        null,
        null,
        null,
        null,
        null,
        null,
        null,
        null,
        null,
        null,
        null,
        null,
        null,
        null,
        null,
        null,
        null,
        null,
        null,
        null,
        null,
        null,
        null,
        null,
        null,
        null,
        null,
        null,
        null,
        null,
        null,
        null,
        null,
        null,
        null,
        null,
        null,
        null,
        null,
        null
      ],
      "peak": 59418,
      "current": 59418
    },
    "ES": {
      "actual": [
        28400,
        27992,
        27880,
        27552,
        27392,
        27132,
        26952,
        26740,
        26744,
        26584,
        26576,
        26608,
        26652,
        26808,
        26884,
        27040,
        28232,
        28992,
        29400,
        29920,
        30904,
        31344,
        31696,
        31928,
        32476,
        32828,
        33196,
        33412,
        null,
        null,
        null,
        null,
        null,
        null,
        null,
        null,
        null,
        null,
        null,
        null,
        null,
        null,
        null,
        null,
        null,
        null,
        null,
        null,
        null,
        null,
        null,
        null,
        null,
        null,
        null,
        null,
        null,
        null,
        null,
        null,
        null,
        null,
        null,
        null,
        null,
        null,
        null,
        null,
        null,
        null,
        null,
        null,
        null,
        null,
        null,
        null,
        null,
        null,
        null,
        null,
        null,
        null,
        null,
        null,
        null,
        null,
        null,
        null,
        null,
        null,
        null,
        null,
        null,
        null,
        null,
        null
      ],
      "peak": 33412,
      "current": 33412
    },
    "BE": {
      "actual": [
        6846,
        6713,
        6612,
        6676,
        6605,
        6552,
        6551,
        6457,
        6623,
        6598,
        6556,
        6625,
        6628,
        6540,
        6501,
        6504,
        6454,
        6509,
        6562,
        6592,
        6638,
        6669,
        6724,
        6773,
        6729,
        6893,
        7033,
        7242,
        null,
        null,
        null,
        null,
        null,
        null,
        null,
        null,
        null,
        null,
        null,
        null,
        null,
        null,
        null,
        null,
        null,
        null,
        null,
        null,
        null,
        null,
        null,
        null,
        null,
        null,
        null,
        null,
        null,
        null,
        null,
        null,
        null,
        null,
        null,
        null,
        null,
        null,
        null,
        null,
        null,
        null,
        null,
        null,
        null,
        null,
        null,
        null,
        null,
        null,
        null,
        null,
        null,
        null,
        null,
        null,
        null,
        null,
        null,
        null,
        null,
        null,
        null,
        null,
        null,
        null,
        null,
        null
      ],
      "peak": 7242,
      "current": 7242
    }
  }
}