{
  "updated": "2026-06-16T10:02:34.410271Z",
  "countries": {
    "FR": {
      "actual": [
        39214,
        38189,
        37767,
        37149,
        36564,
        36005,
        35961,
        35782,
        35666,
        35485,
        35533,
        35738,
        36312,
        36887,
        37370,
        37814,
        38812,
        39647,
        40406,
        41350,
        42462,
        43408,
        44036,
        44768,
        45636,
        46194,
        46768,
        47019,
        47483,
        47603,
        47776,
        47870,
        48130,
        48029,
        47793,
        48038,
        null,
        null,
        null,
        null,
        null,
        null,
        null,
        null,
        null,
        null,
        null,
        null,
        null,
        null,
        null,
        null,
        null,
        null,
        null,
        null,
        null,
        null,
        null,
        null,
        null,
        null,
        null,
        null,
        null,
        null,
        null,
        null,
        null,
        null,
        null,
        null,
        null,
        null,
        null,
        null,
        null,
        null,
        null,
        null,
        null,
        null,
        null,
        null,
        null,
        null,
        null,
        null,
        null,
        null,
        null,
        null,
        null,
        null,
        null,
        null
      ],
      "peak": 48130,
      "current": 48038
    },
    "DE_LU": {
      "actual": [
        43474,
        43249,
        43300,
        43710,
        43428,
        43640,
        43971,
        44218,
        44667,
        44598,
        44495,
        44950,
        46329,
        46863,
        47571,
        46643,
        46540,
        47093,
        47803,
        55131,
        55715,
        56750,
        57424,
        58074,
        58013,
        58878,
        59208,
        59348,
        58774,
        59727,
        60421,
        60947,
        56274,
        54113,
        52257,
        48682,
        45568,
        null,
        null,
        null,
        null,
        null,
        null,
        null,
        null,
        null,
        null,
        null,
        null,
        null,
        null,
        null,
        null,
        null,
        null,
        null,
        null,
        null,
        null,
        null,
        null,
        null,
        null,
        null,
        null,
        null,
        null,
        null,
        null,
        null,
        null,
        null,
        null,
        null,
        null,
        null,
        null,
        null,
        null,
        null,
        null,
        null,
        null,
        null,
        null,
        null,
        null,
        null,
        null,
        null,
        null,
        null,
        null,
        null,
        null,
        null
      ],
      "peak": 60947,
      "current": 45568
    },
    "ES": {
      "actual": [
        25492,
        25256,
        25144,
        25132,
        24692,
        24740,
        24720,
        24728,
        24444,
        24540,
        24652,
        24472,
        24700,
        24908,
        24944,
        25348,
        26408,
        27004,
        27228,
        27644,
        28828,
        29372,
        29944,
        30320,
        30672,
        30808,
        31044,
        31112,
        30904,
        31248,
        31268,
        31292,
        31300,
        31060,
        31348,
        31384,
        31128,
        31056,
        null,
        null,
        null,
        null,
        null,
        null,
        null,
        null,
        null,
        null,
        null,
        null,
        null,
        null,
        null,
        null,
        null,
        null,
        null,
        null,
        null,
        null,
        null,
        null,
        null,
        null,
        null,
        null,
        null,
        null,
        null,
        null,
        null,
        null,
        null,
        null,
        null,
        null,
        null,
        null,
        null,
        null,
        null,
        null,
        null,
        null,
        null,
        null,
        null,
        null,
        null,
        null,
        null,
        null,
        null,
        null,
        null,
        null
      ],
      "peak": 31384,
      "current": 31056
    },
    "BE": {
      "actual": [
        7575,
        7594,
        7570,
        7516,
        7441,
        7626,
        7813,
        7723,
        7697,
        7734,
        7610,
        7615,
        7618,
        7676,
        7710,
        7880,
        8150,
        8287,
        8453,
        8716,
        8806,
        9006,
        9302,
        9431,
        9470,
        9623,
        9912,
        10064,
        10223,
        10231,
        10399,
        10432,
        10226,
        10338,
        10432,
        10509,
        10618,
        10458,
        null,
        null,
        null,
        null,
        null,
        null,
        null,
        null,
        null,
        null,
        null,
        null,
        null,
        null,
        null,
        null,
        null,
        null,
        null,
        null,
        null,
        null,
        null,
        null,
        null,
        null,
        null,
        null,
        null,
        null,
        null,
        null,
        null,
        null,
        null,
        null,
        null,
        null,
        null,
        null,
        null,
        null,
        null,
        null,
        null,
        null,
        null,
        null,
        null,
        null,
        null,
        null,
        null,
        null,
        null,
        null,
        null,
        null
      ],
      "peak": 10618,
      "current": 10458
    }
  }
}